{
  "project_info": {
    "project_number": "175477261411",
    "project_id": "dawakhaana-2",
    "storage_bucket": "dawakhaana-2.firebasestorage.app"
  },
  "client": [
    {
      "client_info": {
        "mobilesdk_app_id": "1:175477261411:android:1cd9a720c140109697e456",
        "android_client_info": {
          "package_name": "com.company.flutter_project"
        }
      },
      "oauth_client": [],
      "api_key": [
        {
          "current_key": "AIzaSyDaK9_pMHGwWl-8KBcnDuTHcXBRQk_AgtA"
        }
      ],
      "services": {
        "appinvite_service": {
          "other_platform_oauth_client": []
        }
      }
    }
  ],
  "configuration_version": "1"
}